MANIFEST.in
README.txt
setup.py
Setup_Janis/gen_names_Janis.py
gen_names_Janis.egg-info/PKG-INFO
gen_names_Janis.egg-info/SOURCES.txt
gen_names_Janis.egg-info/dependency_links.txt
gen_names_Janis.egg-info/requires.txt
gen_names_Janis.egg-info/top_level.txt