Metadata-Version: 1.0
Name: gen-names-Janis
Version: 0.1.0
Summary: Super useful library
Home-page: UNKNOWN
Author: JK company PLC
Author-email: jkarasa@gmail.com
License: UNKNOWN
Platform: UNKNOWN
